fastai_sparse/__init__.py
fastai_sparse/core.py
fastai_sparse/data.py
fastai_sparse/data_items.py
fastai_sparse/datasets.py
fastai_sparse/learner.py
fastai_sparse/metrics.py
fastai_sparse/utils.py
fastai_sparse/version.py
fastai_sparse/callbacks/__init__.py
fastai_sparse/callbacks/csv_logger.py
fastai_sparse/callbacks/tracker.py
fastai_sparse/callbacks/train_val_time.py
fastai_sparse/transforms/__init__.py
fastai_sparse/transforms/affine.py
fastai_sparse/transforms/colors.py
fastai_sparse/transforms/convert.py
fastai_sparse/transforms/main.py
fastai_sparse/transforms/spatial.py
fastai_sparse/visualize/__init__.py
fastai_sparse/visualize/ipyvolume.py
fastai_sparse/visualize/utils.py
fastai_sparse-0.0.10.dist-info/LICENSE
fastai_sparse-0.0.10.dist-info/METADATA
fastai_sparse-0.0.10.dist-info/WHEEL
fastai_sparse-0.0.10.dist-info/top_level.txt
fastai_sparse-0.0.10.dist-info/RECORD
